{
  "updated": "2026-05-03T18:30:33Z",
  "last_checked": "2026-05-03T18:30:33Z",
  "gold_items": [
    {
      "source": "Investing.com 商品先物",
      "title": "中東紛争の中でアルミニウム市場は動揺するも回復力を示す",
      "link": "https://jp.investing.com/news/commodities-news/article-1515735",
      "published": "2026-05-03 16:33:56",
      "isoDate": "2026-05-03T16:33:56Z"
    },
    {
      "source": "Investing.com 商品先物",
      "title": "クウェートの石油生産量、6月に日量262.8万バレルに達する見通し",
      "link": "https://jp.investing.com/news/commodities-news/article-93CH-1515719",
      "published": "2026-05-03 14:55:16",
      "isoDate": "2026-05-03T14:55:16Z"
    },
    {
      "source": "Investing.com 商品先物",
      "title": "UAE離脱にもかかわらず、OPEC+は6月の増産を推進へ―ロイター",
      "link": "https://jp.investing.com/news/commodities-news/article-1515639",
      "published": "2026-05-02 11:00:12",
      "isoDate": "2026-05-02T11:00:12Z"
    },
    {
      "source": "Investing.com 商品先物",
      "title": "UAEのOPEC離脱:石油市場への潜在的影響とは",
      "link": "https://jp.investing.com/news/commodities-news/article-1515635",
      "published": "2026-05-02 09:47:22",
      "isoDate": "2026-05-02T09:47:22Z"
    },
    {
      "source": "Investing.com 商品先物",
      "title": "北西欧州のガソリンマージンが2023年8月以来の高水準に急騰",
      "link": "https://jp.investing.com/news/commodities-news/article-93CH-1515393",
      "published": "2026-05-01 19:45:52",
      "isoDate": "2026-05-01T19:45:52Z"
    },
    {
      "source": "Investing.com 商品先物",
      "title": "米国の石油・ガス掘削リグ、2週連続増加で4月上旬以来の高水準",
      "link": "https://jp.investing.com/news/commodities-news/article-93CH-1515353",
      "published": "2026-05-01 18:42:27",
      "isoDate": "2026-05-01T18:42:27Z"
    },
    {
      "source": "Investing.com 商品先物",
      "title": "ブレント原油価格が急騰していない理由、ヤーデニが解説",
      "link": "https://jp.investing.com/news/commodities-news/article-1515110",
      "published": "2026-05-01 14:56:34",
      "isoDate": "2026-05-01T14:56:34Z"
    },
    {
      "source": "Investing.com 商品先物",
      "title": "ベネズエラの石油輸出が14%増加、7年超ぶりの高水準に",
      "link": "https://jp.investing.com/news/commodities-news/article-93CH-1515095",
      "published": "2026-05-01 14:56:05",
      "isoDate": "2026-05-01T14:56:05Z"
    },
    {
      "source": "Investing.com 商品先物",
      "title": "日本、通貨変動を受けて原油先物市場への介入準備を表明",
      "link": "https://jp.investing.com/news/commodities-news/article-93CH-1514573",
      "published": "2026-05-01 11:27:15",
      "isoDate": "2026-05-01T11:27:15Z"
    },
    {
      "source": "Investing.com 商品先物",
      "title": "イラン紛争長期化で欧州ガス価格が上昇",
      "link": "https://jp.investing.com/news/commodities-news/article-1514335",
      "published": "2026-05-01 10:00:45",
      "isoDate": "2026-05-01T10:00:45Z"
    }
  ],
  "usdjpy_items": [
    {
      "source": "Investing.com 外為",
      "title": "ベセント財務長官、エネルギー価格は年内に下落すると発言",
      "link": "https://jp.investing.com/news/economy-news/article-1515718",
      "published": "2026-05-03 14:50:44",
      "isoDate": "2026-05-03T14:50:44Z"
    },
    {
      "source": "Investing.com 外為",
      "title": "S&P 500の上昇が弱い市場の広がりを隠す中、小型株が注目を集める",
      "link": "https://jp.investing.com/news/stock-market-news/article-1515695",
      "published": "2026-05-03 12:43:28",
      "isoDate": "2026-05-03T12:43:28Z"
    },
    {
      "source": "Investing.com 外為",
      "title": "AIへの投資が2027年度には設備投資を1兆ドルに押し上げる可能性",
      "link": "https://jp.investing.com/news/economy-news/article-1515687",
      "published": "2026-05-03 09:55:09",
      "isoDate": "2026-05-03T09:55:09Z"
    },
    {
      "source": "Investing.com 外為",
      "title": "ビットコイン、規制進展とS&P500最高値更新で8万ドルを目指す",
      "link": "https://jp.investing.com/news/cryptocurrency-news/article-1515684",
      "published": "2026-05-03 09:17:15",
      "isoDate": "2026-05-03T09:17:15Z"
    },
    {
      "source": "Investing.com 外為",
      "title": "アナリストのAI関連5大動向:JPモルガン・チェース・アンド・カンパニーがMetaを格下げ、マイクロンテクノロジー.がウォール街最高値の目標株価を獲得",
      "link": "https://jp.investing.com/news/stock-market-news/article-1515683",
      "published": "2026-05-03 09:00:02",
      "isoDate": "2026-05-03T09:00:02Z"
    },
    {
      "source": "Investing.com 外為",
      "title": "日本、中国の供給リスクに対抗すべく豪州の重要鉱物を標的に",
      "link": "https://jp.investing.com/news/economy-news/article-1515680",
      "published": "2026-05-03 08:16:42",
      "isoDate": "2026-05-03T08:16:42Z"
    },
    {
      "source": "Investing.com 外為",
      "title": "AIブームと石油輸出が戦争リスクを相殺、新興市場が過去最高値を記録",
      "link": "https://jp.investing.com/news/economy-news/article-1515675",
      "published": "2026-05-03 07:00:29",
      "isoDate": "2026-05-03T07:00:29Z"
    },
    {
      "source": "Investing.com 外為",
      "title": "世界株式は高値圏にあるが、なぜポジショニングは依然として遅れているのか",
      "link": "https://jp.investing.com/news/stock-market-news/article-1515665",
      "published": "2026-05-03 03:40:56",
      "isoDate": "2026-05-03T03:40:56Z"
    },
    {
      "source": "Investing.com 外為",
      "title": "Nvidiaのフィジカル AI への転換がアジアのサプライチェーン全体で上昇相場を引き起こす",
      "link": "https://jp.investing.com/news/economy-news/article-1515662",
      "published": "2026-05-03 02:34:51",
      "isoDate": "2026-05-03T02:34:51Z"
    },
    {
      "source": "Investing.com 外為",
      "title": "ゴールデンウィーク中の為替介入疑惑について片山財務相がコメント拒否",
      "link": "https://jp.investing.com/news/economy-news/article-1515659",
      "published": "2026-05-03 01:47:33",
      "isoDate": "2026-05-03T01:47:33Z"
    }
  ],
  "btc_items": [
    {
      "source": "CoinPost",
      "title": "ビットコインFOMC通過後も1200万円台で推移、来週の米雇用統計に注目｜bitbankアナリスト寄稿",
      "link": "https://coinpost.jp/?p=706431",
      "published": "Sun, 03 May 2026 11:30:02 +0900",
      "isoDate": "2026-05-03T02:30:02Z"
    },
    {
      "source": "CoinPost",
      "title": "今週の主要仮想通貨材料まとめ、チューダー・ジョーンズのBTC評価やリップル幹部のXRPLの展望など",
      "link": "https://coinpost.jp/?p=706296",
      "published": "Sun, 03 May 2026 09:30:06 +0900",
      "isoDate": "2026-05-03T00:30:06Z"
    },
    {
      "source": "CoinPost",
      "title": "週刊仮想通貨ニュース｜米ビットコイン準備金の重大発表予告や米クラリティー法案の進展に高い関心",
      "link": "https://coinpost.jp/?p=706326",
      "published": "Sun, 03 May 2026 09:25:41 +0900",
      "isoDate": "2026-05-03T00:25:41Z"
    },
    {
      "source": "CoinPost",
      "title": "台湾でビットコイン「国家戦略資産化」の動き、外貨準備への組み入れを提言",
      "link": "https://coinpost.jp/?p=706613",
      "published": "Sat, 02 May 2026 14:30:06 +0900",
      "isoDate": "2026-05-02T05:30:06Z"
    },
    {
      "source": "CoinPost",
      "title": "米クラリティー法案が重要局面に、マークアップに向け前進",
      "link": "https://coinpost.jp/?p=706600",
      "published": "Sat, 02 May 2026 13:25:36 +0900",
      "isoDate": "2026-05-02T04:25:36Z"
    },
    {
      "source": "CoinPost",
      "title": "カナダ年金基金AIMCo、約267億円でマイクストラテジー株を購入",
      "link": "https://coinpost.jp/?p=706598",
      "published": "Sat, 02 May 2026 11:44:48 +0900",
      "isoDate": "2026-05-02T02:44:48Z"
    },
    {
      "source": "CoinPost",
      "title": "コインベースら、6月末までの仮想通貨市場の回復を予測　BTC・ETH分析も",
      "link": "https://coinpost.jp/?p=706587",
      "published": "Sat, 02 May 2026 11:02:19 +0900",
      "isoDate": "2026-05-02T02:02:19Z"
    },
    {
      "source": "CoinPost",
      "title": "ビットコイン採掘企業ライオットQ1決算、AIデータセンター事業が収益の20%へ急成長",
      "link": "https://coinpost.jp/?p=706557",
      "published": "Sat, 02 May 2026 09:55:07 +0900",
      "isoDate": "2026-05-02T00:55:07Z"
    },
    {
      "source": "CoinPost",
      "title": "ブラジル中央銀行、規制下の国際決済での仮想通貨利用を禁止へ",
      "link": "https://coinpost.jp/?p=706572",
      "published": "Sat, 02 May 2026 07:40:57 +0900",
      "isoDate": "2026-05-01T22:40:57Z"
    },
    {
      "source": "CoinPost",
      "title": "量子コンピュータの脅威から休眠ビットコインを守る新提案「PACTs」、サトシの資産も対象",
      "link": "https://coinpost.jp/?p=706560",
      "published": "Sat, 02 May 2026 05:55:38 +0900",
      "isoDate": "2026-05-01T20:55:38Z"
    }
  ]
}